spine/__init__.py
spine/banner.py
spine/driver.py
spine/main.py
spine/version.py
spine/ana/__init__.py
spine/ana/base.py
spine/ana/factories.py
spine/ana/manager.py
spine/ana/template.py
spine/ana/calib/__init__.py
spine/ana/calib/mcs.py
spine/ana/diag/__init__.py
spine/ana/diag/shower.py
spine/ana/diag/track.py
spine/ana/metric/__init__.py
spine/ana/metric/cluster.py
spine/ana/metric/optical.py
spine/ana/metric/point.py
spine/ana/metric/segment.py
spine/ana/script/__init__.py
spine/ana/script/save.py
spine/bin/__init__.py
spine/bin/cli.py
spine/config/__init__.py
spine/config/api.py
spine/config/download.py
spine/config/errors.py
spine/config/loader.py
spine/config/meta.py
spine/construct/__init__.py
spine/construct/base.py
spine/construct/fragment.py
spine/construct/interaction.py
spine/construct/manager.py
spine/construct/particle.py
spine/data/__init__.py
spine/data/base.py
spine/data/crt.py
spine/data/list.py
spine/data/meta.py
spine/data/neutrino.py
spine/data/optical.py
spine/data/particle.py
spine/data/run_info.py
spine/data/trigger.py
spine/data/batch/__init__.py
spine/data/batch/base.py
spine/data/batch/edge_index.py
spine/data/batch/index.py
spine/data/batch/tensor.py
spine/data/out/__init__.py
spine/data/out/base.py
spine/data/out/fragment.py
spine/data/out/interaction.py
spine/data/out/particle.py
spine/geo/__init__.py
spine/geo/base.py
spine/geo/factories.py
spine/geo/manager.py
spine/geo/config/2x2/2x2_mr4-5_geometry.yaml
spine/geo/config/2x2/2x2_mr5-0_geometry.yaml
spine/geo/config/2x2/2x2_mr6-0_geometry.yaml
spine/geo/config/2x2/2x2_mr6-1_geometry.yaml
spine/geo/config/2x2/2x2_mr6-2_geometry.yaml
spine/geo/config/2x2/2x2_mr6-3_geometry.yaml
spine/geo/config/2x2/2x2_mr6-4_geometry.yaml
spine/geo/config/2x2/2x2_mr6-5_geometry.yaml
spine/geo/config/2x2-single/2x2-single_mr5-0_geometry.yaml
spine/geo/config/2x2-single/2x2-single_mr6-5_geometry.yaml
spine/geo/config/dune10kt-1x2x6/dune10kt-1x2x6_geometry.yaml
spine/geo/config/fsd/fsd_cr1_geometry.yaml
spine_ml-0.9.4.dist-info/LICENSE
spine_ml-0.9.4.dist-info/METADATA
spine_ml-0.9.4.dist-info/WHEEL
spine_ml-0.9.4.dist-info/entry_points.txt
spine_ml-0.9.4.dist-info/top_level.txt
spine_ml-0.9.4.dist-info/RECORD
