Metadata-Version: 2.1
Name: spine-ml
Version: 0.9.4
Summary: SPINE: Scalable Particle Imaging with Neural Embeddings for 3D high energy physics data analysis
Author-email: DeepLearnPhysics Collaboration <drielsma@stanford.edu>
Maintainer-email: Francois Drielsma <drielsma@stanford.edu>
License: MIT
Project-URL: Homepage, https://github.com/DeepLearnPhysics/spine
Project-URL: Repository, https://github.com/DeepLearnPhysics/spine.git
Project-URL: Documentation, https://spine.readthedocs.io/
Project-URL: Bug Tracker, https://github.com/DeepLearnPhysics/spine/issues
Keywords: machine learning,physics,neutrino,sparse convolution,graph neural network
Classifier: Development Status :: 4 - Beta
Classifier: Intended Audience :: Science/Research
Classifier: License :: OSI Approved :: MIT License
Classifier: Operating System :: OS Independent
Classifier: Programming Language :: Python :: 3
Classifier: Programming Language :: Python :: 3.8
Classifier: Programming Language :: Python :: 3.9
Classifier: Programming Language :: Python :: 3.10
Classifier: Programming Language :: Python :: 3.11
Classifier: Topic :: Scientific/Engineering :: Physics
Classifier: Topic :: Scientific/Engineering :: Artificial Intelligence
Requires-Python: >=3.8
License-File: LICENSE
Requires-Dist: numexpr>=2.8.0
Requires-Dist: numpy>=1.19.0
Requires-Dist: scipy>=1.7.0
Requires-Dist: pandas>=1.3.0
Requires-Dist: PyYAML>=5.4.0
Requires-Dist: h5py>=3.1.0
Requires-Dist: numba>=0.56.0
Requires-Dist: psutil>=5.8.0
Requires-Dist: tqdm>=4.60.0
Provides-Extra: all
Requires-Dist: spine[viz]; extra == "all"
Requires-Dist: spine[dev]; extra == "all"
Provides-Extra: core
Provides-Extra: dev
Requires-Dist: pytest>=6.0.0; extra == "dev"
Requires-Dist: pytest-cov>=2.10.0; extra == "dev"
Requires-Dist: black>=23.0.0; extra == "dev"
Requires-Dist: flake8>=6.0.0; extra == "dev"
Requires-Dist: isort>=5.12.0; extra == "dev"
Requires-Dist: pre-commit>=3.0.0; extra == "dev"
Requires-Dist: build>=0.8.0; extra == "dev"
Requires-Dist: twine>=4.0.0; extra == "dev"
Requires-Dist: wheel>=0.38.0; extra == "dev"
Requires-Dist: sphinx>=4.0.0; extra == "dev"
Requires-Dist: sphinx-rtd-theme>=1.0.0; extra == "dev"
Requires-Dist: sphinx-copybutton>=0.5.0; extra == "dev"
Requires-Dist: numpydoc>=1.4.0; extra == "dev"
Provides-Extra: viz
Requires-Dist: matplotlib>=3.3.0; extra == "viz"
Requires-Dist: plotly>=4.14.0; extra == "viz"
Requires-Dist: seaborn>=0.11.0; extra == "viz"
